Metadata-Version: 2.1
Name: logger-rewrite
Version: 0.3
Summary: log scripts
Home-page: https://github.com/cuongngm/logger_rewrite
Author: cuongngm
Author-email: cuonghip0908@gmail.com
License: UNKNOWN
Platform: UNKNOWN
Classifier: Programming Language :: Python :: 3
Classifier: License :: OSI Approved :: MIT License
Classifier: Operating System :: OS Independent
Requires-Python: >=3.6
